<?xml version="1.0" encoding="UTF-8"?>
<beans xmlns="http://www.springframework.org/schema/beans"
       xmlns:xsi="http://www.w3.org/2001/XMLSchema-instance"
       xmlns:context="http://www.springframework.org/schema/context"
       xmlns:security="http://www.springframework.org/schema/security"
       xmlns:tx="http://www.springframework.org/schema/tx"
       xsi:schemaLocation="http://www.springframework.org/schema/security
        http://www.springframework.org/schema/security/spring-security-4.1.xsd
		http://www.springframework.org/schema/beans
		http://www.springframework.org/schema/beans/spring-beans.xsd
		http://www.springframework.org/schema/context
		http://www.springframework.org/schema/context/spring-context-4.2.xsd
		 http://www.springframework.org/schema/tx
		 http://www.springframework.org/schema/tx/spring-tx.xsd">


    <context:annotation-config/>
    <context:component-scan base-package="com.rog.webshop"/>


    <context:property-placeholder location="classpath:application.properties"/>

    <bean id="dataSource" class="org.apache.commons.dbcp.BasicDataSource" destroy-method="close">

        <property name="driverClassName" value="${jdbc.driver}"/>
        <property name="url" value="${jdbc.url}"/>
        <property name="password" value="${jdbc.password}"/>
        <property name="username" value="${jdbc.username}"/>
    </bean>

    <bean id="transactionManager"
          class="org.springframework.jdbc.datasource.DataSourceTransactionManager">
        <property name="dataSource" ref="dataSource"></property>
    </bean>
    <tx:annotation-driven transaction-manager="transactionManager"/>


    <bean id="sessionFactory"
          class="org.springframework.orm.hibernate5.LocalSessionFactoryBean">
        <property name="dataSource" ref="dataSource"></property>
        <property name="hibernateProperties">
            <props>
                <prop key="hibernate.dialect">${hibernate.dialect}</prop>
                <prop key="hibernate.show_sql">${hibernate.show_sql}</prop>
                <prop key="hibernate.format_sql">${hibernate.format_sql}</prop>
            </props>
        </property>
        <property name="packagesToScan">
            <list>
                <value>com.rog.webshop.model</value>
            </list>
        </property>
    </bean>

    <bean id="passwordEncoder" class="org.springframework.security.crypto.password.StandardPasswordEncoder"/>

    <bean id="customUserDetailsService" class="com.rog.webshop.service.CustomUserDetailsService"/>

    <bean id="customSuccessHandler" class="com.rog.webshop.configuration.CustomSuccessHandler"/>

    <security:authentication-manager>
        <security:authentication-provider user-service-ref="customUserDetailsService"/>
    </security:authentication-manager>


    <security:http use-expressions="true" auto-config="true">
        <!--<security:csrf disabled="true"/>-->
        <!-- Login system config -->
        <security:intercept-url pattern="/" access="permitAll"/>
        <security:intercept-url pattern="/home" access="permitAll"/>
        <security:intercept-url pattern="/admin" access="hasRole('ADMIN')"/>
        <security:intercept-url pattern="/db" access="hasRole('ADMIN') and hasRole('DBA')"/>
        <security:form-login login-page="/login"
                             username-parameter="ssoId"
                             password-parameter="password"
                             authentication-success-handler-ref="customSuccessHandler"/>
        <security:access-denied-handler error-page="/Access_Denied"/>
        <security:csrf disabled="true"/>
    </security:http>

    <security:global-method-security secured-annotations="enabled"></security:global-method-security>

</beans>